__init__.py
botik_vkbottle/__init__.py
botik_vkbottle/app.py
botik_vkbottle/api/__init__.py
botik_vkbottle/api/api.py
botik_vkbottle/api/api_type.py
botik_vkbottle/api/send_message.py
botik_vkbottle/api/attachment_handlers/__init__.py
botik_vkbottle/api/attachment_handlers/photo_attachment_handler.py
botik_vkbottle/input/__init__.py
botik_vkbottle/input/keyboard/__init__.py
botik_vkbottle/input/keyboard/keyboard_markup.py
botik_vkbottle/input/keyboard/markup_factory.py
botik_vkbottle/input/keyboard/button/__init__.py
botik_vkbottle/input/keyboard/button/button.py
botik_vkbottle/input/keyboard/button/button_factory.py
botik_vkbottle/input/message_handlers/__init__.py
botik_vkbottle/input/message_handlers/raw_message_handlers.py
botik_vkbottle/page/__init__.py
botik_vkbottle/page/page_factory.py
botik_vkbottle-0.0.1.dist-info/LICENSE
botik_vkbottle-0.0.1.dist-info/METADATA
botik_vkbottle-0.0.1.dist-info/WHEEL
botik_vkbottle-0.0.1.dist-info/top_level.txt
botik_vkbottle-0.0.1.dist-info/RECORD
