Metadata-Version: 2.1
Name: botik-vkbottle
Version: 0.0.1
Summary: Extension for Botik to support VKBottle
Author-email: dasstyx <dasstyx@gmail.com>
Project-URL: Documentation, https://botik.readthedocs.io
Project-URL: Homepage, https://github.com/dasstyx/botik-vkbottle
Project-URL: Bug Tracker, https://github.com/dasstyx/botik-vkbottle/issues
Keywords: api,framework,bot,vk,messenger,async,botik
Classifier: Programming Language :: Python :: 3
Classifier: License :: OSI Approved :: MIT License
Classifier: Operating System :: OS Independent
Requires-Python: >=3.7
License-File: LICENSE
Requires-Dist: botik
Requires-Dist: vkbottle (==4.3.10)
